authtools.py
authtools-0.0.3.dist-info/LICENCE.txt
authtools-0.0.3.dist-info/METADATA
authtools-0.0.3.dist-info/WHEEL
authtools-0.0.3.dist-info/top_level.txt
authtools-0.0.3.dist-info/RECORD
